physunits/__init__.py
physunits/angle.py
physunits/electromagnetic.py
physunits/energy.py
physunits/frequency.py
physunits/length.py
physunits/mass.py
physunits/other.py
physunits/power.py
physunits/pressure.py
physunits/temperature.py
physunits/time_units.py
physunits-1.0.3.dist-info/LICENSE.txt
physunits-1.0.3.dist-info/METADATA
physunits-1.0.3.dist-info/WHEEL
physunits-1.0.3.dist-info/top_level.txt
physunits-1.0.3.dist-info/RECORD
