Metadata-Version: 2.1
Name: physunits
Version: 1.0.3
Summary: Physical units as global variables for simple numerical propagation
Home-page: https://github.com/pacosalces/physunits
Author: pacosalces
Author-email: pacosalces@gmail.com
License: LICENSE.txt
Platform: UNKNOWN
Classifier: Programming Language :: Python :: 3
Classifier: License :: OSI Approved :: MIT License
Classifier: Operating System :: OS Independent
Requires-Python: >=3.6
License-File: LICENSE.txt
